ldt_people_client_staging/__init__.py
ldt_people_client_staging/api_client.py
ldt_people_client_staging/api_response.py
ldt_people_client_staging/configuration.py
ldt_people_client_staging/exceptions.py
ldt_people_client_staging/py.typed
ldt_people_client_staging/rest.py
ldt_people_client_staging/api/__init__.py
ldt_people_client_staging/api/search_api.py
ldt_people_client_staging/api/verification_api.py
ldt_people_client_staging/models/__init__.py
ldt_people_client_staging/models/agg_request.py
ldt_people_client_staging/models/agg_response.py
ldt_people_client_staging/models/agg_response_buckets_inner.py
ldt_people_client_staging/models/company.py
ldt_people_client_staging/models/filter_group.py
ldt_people_client_staging/models/filter_group_filters_inner.py
ldt_people_client_staging/models/find200_response.py
ldt_people_client_staging/models/find200_response_matches_inner.py
ldt_people_client_staging/models/find200_response_matches_inner_people_inner.py
ldt_people_client_staging/models/find_preview200_response.py
ldt_people_client_staging/models/find_preview200_response_matches_inner.py
ldt_people_client_staging/models/find_preview200_response_matches_inner_people_inner.py
ldt_people_client_staging/models/find_preview_request.py
ldt_people_client_staging/models/find_preview_request_matches_inner.py
ldt_people_client_staging/models/find_preview_request_matches_inner_fields_inner.py
ldt_people_client_staging/models/find_request.py
ldt_people_client_staging/models/find_request_matches_inner.py
ldt_people_client_staging/models/find_request_matches_inner_fields_inner.py
ldt_people_client_staging/models/get_person_by_ldp200_response.py
ldt_people_client_staging/models/job.py
ldt_people_client_staging/models/location_details.py
ldt_people_client_staging/models/lookup_persons_by_ids200_response.py
ldt_people_client_staging/models/lookup_persons_by_ids_request.py
ldt_people_client_staging/models/person.py
ldt_people_client_staging/models/person_education_inner.py
ldt_people_client_staging-1.0.81.dist-info/METADATA
ldt_people_client_staging-1.0.81.dist-info/WHEEL
ldt_people_client_staging-1.0.81.dist-info/top_level.txt
ldt_people_client_staging-1.0.81.dist-info/RECORD
