Metadata-Version: 2.2
Name: ldt-people-client-staging
Version: 1.0.81
Summary: Live Data People API
Home-page: 
Author: Live Data Technologies
Author-email: support@livedatatechnologies.com
License: Attribution-NoDerivs
Keywords: OpenAPI,OpenAPI-Generator,Live Data People API
Requires-Dist: urllib3<3.0.0,>=1.25.3
Requires-Dist: python-dateutil>=2.8.2
Requires-Dist: pydantic>=2
Requires-Dist: typing-extensions>=4.7.1
Dynamic: author
Dynamic: author-email
Dynamic: description
Dynamic: description-content-type
Dynamic: keywords
Dynamic: license
Dynamic: requires-dist
Dynamic: summary
